int_to_byte/setup.py
int_to_byte.egg-info/PKG-INFO
int_to_byte.egg-info/SOURCES.txt
int_to_byte.egg-info/dependency_links.txt
int_to_byte.egg-info/not-zip-safe
int_to_byte.egg-info/top_level.txt