Metadata-Version: 1.0
Name: int-to-byte
Version: 0.1
Summary: converter numbers from int to byte
Home-page: https://github.com/AlexOdlin/lab8
Author: Alexandr Sokolov IU8-27
Author-email: UNKNOWN
License: BMSTU
Platform: UNKNOWN
